emerge/__init__.py
emerge/constants.py
emerge/cli/__init__.py
emerge/cli/cli.py
emerge/cli/get_num_core.py
emerge/cli/get_observers.py
emerge/cli/multiscenario_metrics.py
emerge/cli/nodal_hosting_capacity.py
emerge/cli/nodal_hosting_sqlite_tables.py
emerge/cli/scenario.py
emerge/cli/schema_generator.py
emerge/cli/timeseries_simulation.py
emerge/metrics/__init__.py
emerge/metrics/data_model.py
emerge/metrics/exceptions.py
emerge/metrics/line_loading_stats.py
emerge/metrics/node_metrics.py
emerge/metrics/node_voltage_stats.py
emerge/metrics/observer.py
emerge/metrics/system_metrics.py
emerge/network/__init__.py
emerge/network/asset_metrics.py
emerge/network/data_model.py
emerge/network/feeder_geojson.py
emerge/scenarios/__init__.py
emerge/scenarios/data_model.py
emerge/scenarios/opendss_writer.py
emerge/scenarios/scenario.py
emerge/scenarios/selection_strategy.py
emerge/scenarios/sizing_strategy.py
emerge/simulator/__init__.py
emerge/simulator/opendss.py
emerge/simulator/powerflow_results.py
emerge/simulator/simulation_manager.py
emerge/utils/__init__.py
emerge/utils/dss_util.py
emerge/utils/util.py
nrel_emerge-2.0.0.dist-info/METADATA
nrel_emerge-2.0.0.dist-info/WHEEL
nrel_emerge-2.0.0.dist-info/entry_points.txt
nrel_emerge-2.0.0.dist-info/licenses/LICENSE.txt
nrel_emerge-2.0.0.dist-info/RECORD
