Metadata-Version: 2.3
Name: NREL-emerge
Version: 2.0.0
Summary: Emerging technologies Management and Risk evaluation on distributions Grid Evolution
Project-URL: Documentation, https://github.com/NREL/EMeRGE#readme
Project-URL: Issues, https://github.com/NREL/EMeRGE/issues
Project-URL: Source, https://github.com/NREL/EMeRGE/grid-data-models
Author-email: Kapil Duwadi <kapil.duwadi@nrel.gov>
License-File: LICENSE.txt
Keywords: DER,Distribution,System,analysis,impact,management,risk,technologies
Classifier: License :: OSI Approved :: BSD License
Classifier: Operating System :: OS Independent
Classifier: Programming Language :: Python :: 3.11
Requires-Python: >=3.11
Requires-Dist: click
Requires-Dist: json5
Requires-Dist: loguru
Requires-Dist: networkx
Requires-Dist: opendssdirect-py==0.8.4
Requires-Dist: pandas
Requires-Dist: polars
Requires-Dist: psutil
Requires-Dist: pyarrow
Requires-Dist: pydantic
Requires-Dist: pyyaml
Requires-Dist: sqlmodel
Provides-Extra: dev
Requires-Dist: pre-commit; extra == 'dev'
Requires-Dist: pytest; extra == 'dev'
Requires-Dist: pytest-cov; extra == 'dev'
Requires-Dist: ruff; extra == 'dev'
Provides-Extra: doc
Requires-Dist: autodoc-pydantic; extra == 'doc'
Requires-Dist: myst-parser; extra == 'doc'
Requires-Dist: pydata-sphinx-theme; extra == 'doc'
Requires-Dist: sphinx; extra == 'doc'
Requires-Dist: sphinxcontrib-mermaid; extra == 'doc'
